vibe_coded_decorator/__init__.py
vibe_coded_decorator-0.1.1.dist-info/METADATA
vibe_coded_decorator-0.1.1.dist-info/WHEEL
vibe_coded_decorator-0.1.1.dist-info/top_level.txt
vibe_coded_decorator-0.1.1.dist-info/RECORD
