Metadata-Version: 2.4
Name: vibe-coded-decorator
Version: 0.1.1
Summary: A decorator to mark functions as vibe-coded in their docstrings
Author-email: Sep Keucheni <septimber@gmail.com>
License: MIT
Project-URL: Homepage, https://github.com/sepkeuchenius/vibe-coded-decorator
Project-URL: Repository, https://github.com/sepkeuchenius/vibe-coded-decorator
Keywords: decorator,docstring,vibe-coding,fastapi
Classifier: Development Status :: 4 - Beta
Classifier: Intended Audience :: Developers
Classifier: License :: OSI Approved :: MIT License
Classifier: Programming Language :: Python :: 3
Classifier: Programming Language :: Python :: 3.7
Classifier: Programming Language :: Python :: 3.8
Classifier: Programming Language :: Python :: 3.9
Classifier: Programming Language :: Python :: 3.10
Classifier: Programming Language :: Python :: 3.11
Classifier: Programming Language :: Python :: 3.12
Requires-Python: >=3.7
Provides-Extra: dev
Requires-Dist: pytest>=7.0.0; extra == "dev"
